rigatoni/__init__.py
rigatoni/byte_server.py
rigatoni/core.py
rigatoni/noodle_objects.py
rigatoni/geometry/__init__.py
rigatoni/geometry/methods.py
rigatoni/geometry/objects.py
rigatoni-0.2.8.dist-info/WHEEL
rigatoni-0.2.8.dist-info/METADATA
rigatoni-0.2.8.dist-info/RECORD
