Metadata-Version: 2.1
Name: rigatoni
Version: 0.2.8
Summary: Python Server Library for NOODLES Protocol
Keywords: noodles,cbor,Websockets,server,NOODLES
Author: Alex Racapé
Requires-Python: >=3.8
Classifier: Intended Audience :: Science/Research
Classifier: Programming Language :: Python :: 3
Classifier: Topic :: Scientific/Engineering :: Visualization
Requires-Dist: websockets==11.0.3
Requires-Dist: cbor2==5.4.6
Requires-Dist: pydantic==2.1.1
Requires-Dist: numpy ; extra == "geometry"
Requires-Dist: meshio ; extra == "geometry"
Requires-Dist: pytest ; extra == "testing"
Requires-Dist: penne ; extra == "testing"
Requires-Dist: pandas ; extra == "testing"
Requires-Dist: matplotlib ; extra == "testing"
Requires-Dist: meshio ; extra == "testing"
Requires-Dist: pymeshlab ; extra == "testing"
Project-URL: Documentation, https://insightcenternoodles.github.io/Rigatoni/
Project-URL: Source, https://github.com/InsightCenterNoodles/Rigatoni
Provides-Extra: geometry
Provides-Extra: testing
